pytorch_tabr/__init__.py
pytorch_tabr/arch.py
pytorch_tabr/base_model.py
pytorch_tabr/callbacks.py
pytorch_tabr/dataloader.py
pytorch_tabr/embeddings.py
pytorch_tabr/metrics.py
pytorch_tabr/models.py
pytorch_tabr/utils.py
pytorch_tabr-0.1.0.dist-info/METADATA
pytorch_tabr-0.1.0.dist-info/WHEEL
pytorch_tabr-0.1.0.dist-info/RECORD
