Metadata-Version: 2.1
Name: pytorch-tabr
Version: 0.1.0
Summary: 
Author: Eduardo Carvalho Pinto
Requires-Python: >=3.9,<3.13
Classifier: Programming Language :: Python :: 3
Classifier: Programming Language :: Python :: 3.9
Classifier: Programming Language :: Python :: 3.10
Classifier: Programming Language :: Python :: 3.11
Requires-Dist: black (>=23.9.1,<24.0.0)
Requires-Dist: catboost (>=1.2.2,<2.0.0)
Requires-Dist: delu (>=0.0.22,<0.0.23)
Requires-Dist: einops (>=0.7.0,<0.8.0)
Requires-Dist: faiss-gpu (>=1.7.2,<2.0.0)
Requires-Dist: flake8 (>=6.1.0,<7.0.0)
Requires-Dist: ipython (>=8.17.2,<9.0.0)
Requires-Dist: ipywidgets (>=8.1.1,<9.0.0)
Requires-Dist: notebook (>=7.0.4,<8.0.0)
Requires-Dist: numpy (==1.26.0)
Requires-Dist: pandas (>=2.1.1,<3.0.0)
Requires-Dist: plotly (>=5.17.0,<6.0.0)
Requires-Dist: scikit-learn (>=1.3.1,<2.0.0)
Requires-Dist: torch (>=2.0.0,!=2.0.1)
Requires-Dist: torchvision (>=0.15.1,<0.16.0,!=0.15.2)
Requires-Dist: tqdm (>=4.66.1,<5.0.0)
Requires-Dist: ucimlrepo (>=0.0.3,<0.0.4)
Requires-Dist: xgboost (>=2.0.0,<3.0.0)
